finance_manager/__init__.py
finance_manager/_version.py
finance_manager/config.py
finance_manager/functions.py
finance_manager/cli/__init__.py
finance_manager/cli/__main__.py
finance_manager/cli/docs.py
finance_manager/cli/recharge.py
finance_manager/cli/claims/__init__.py
finance_manager/cli/claims/export.py
finance_manager/cli/claims/load.py
finance_manager/cli/cm/__init__.py
finance_manager/cli/cm/actuals.py
finance_manager/cli/cm/curriculum.py
finance_manager/cli/cm/input.py
finance_manager/cli/db/__init__.py
finance_manager/cli/db/crud.py
finance_manager/cli/db/loadcsv.py
finance_manager/cli/db/syncviews.py
finance_manager/cli/finance/__init__.py
finance_manager/cli/finance/_reconciliation.py
finance_manager/cli/finance/export.py
finance_manager/cli/finance/load.py
finance_manager/cli/finance/save.py
finance_manager/cli/finance/transactions.py
finance_manager/cli/ops/__init__.py
finance_manager/cli/ops/copyset.py
finance_manager/cli/ops/modspine.py
finance_manager/cli/ops/move.py
finance_manager/cli/ops/movestaff.py
finance_manager/cli/ops/newset.py
finance_manager/cli/ops/oncost.py
finance_manager/cli/permissions/__init__.py
finance_manager/cli/permissions/add.py
finance_manager/cli/permissions/director.py
finance_manager/cli/settings/__init__.py
finance_manager/cli/settings/configure.py
finance_manager/cli/settings/display.py
finance_manager/database/__init__.py
finance_manager/database/functions.py
finance_manager/database/replaceable.py
finance_manager/database/spec.py
finance_manager/database/views/__init__.py
finance_manager/database/views/v_calc_claim.py
finance_manager/database/views/v_calc_finances.py
finance_manager/database/views/v_calc_forecast.py
finance_manager/database/views/v_calc_internal_balance.py
finance_manager/database/views/v_calc_monthly_total.py
finance_manager/database/views/v_calc_set_costing.py
finance_manager/database/views/v_calc_staff_fte.py
finance_manager/database/views/v_calc_staff_monthly.py
finance_manager-1.1.1.dist-info/LICENSE
finance_manager-1.1.1.dist-info/METADATA
finance_manager-1.1.1.dist-info/WHEEL
finance_manager-1.1.1.dist-info/entry_points.txt
finance_manager-1.1.1.dist-info/top_level.txt
finance_manager-1.1.1.dist-info/RECORD
