Metadata-Version: 2.1
Name: finance-manager
Version: 1.1.1
Summary: Managing HE Financial Forecasting and Planning
Home-page: https://github.com/jehboyes/finance_manager
Author: James Boyes
Author-email: James.Boyes@lcm.ac.uk
License: UNKNOWN
Platform: UNKNOWN
Requires-Dist: Click
